electronunitconverter/B.py
electronunitconverter/Formatting.py
electronunitconverter/QuantityABC.py
electronunitconverter/T.py
electronunitconverter/V.py
electronunitconverter/__init__.py
electronunitconverter/__main__.py
electronunitconverter/converter.py
electronunitconverter/errors.py
electronunitconverter/py.typed
tests/test_B.py
tests/test_T.py
tests/test_V.py
tests/test_parser.py
tests/test_units.py
electronunitconverter-1.1.1.dist-info/LICENSE
electronunitconverter-1.1.1.dist-info/METADATA
electronunitconverter-1.1.1.dist-info/WHEEL
electronunitconverter-1.1.1.dist-info/entry_points.txt
electronunitconverter-1.1.1.dist-info/top_level.txt
electronunitconverter-1.1.1.dist-info/RECORD
