Metadata-Version: 2.1
Name: electronunitconverter
Version: 1.1.1
Summary: A CLI tool to convert units.
Author: Lorenzo Peri
License: GNU GENERAL PUBLIC LICENSE
Project-URL: Homepage, https://github.com/LorenzoPeri17/electronunitconverter
Requires-Python: >=3.9
License-File: LICENSE
Requires-Dist: scipy
Provides-Extra: test
Requires-Dist: pytest ; extra == 'test'
Requires-Dist: numpy ; extra == 'test'
